gradefetcher/__init__.py
gradefetcher/gradefetcher.py
gradefetcher/static/README.txt
gradefetcher/static/css/gradefetcher.css
gradefetcher/static/html/gradefetcher.html
gradefetcher/static/html/studio_edit.html
gradefetcher/static/js/src/gradefetcher.js
gradefetcher/static/js/src/studio_edit.js
gradefetcher/translations/README.txt
gradefetcher/translations/config.yaml
gradefetcher/translations/ar/LC_MESSAGES/text.mo
gradefetcher/translations/ar/LC_MESSAGES/text.po
gradefetcher/translations/conf/locale/config.yaml
gradefetcher/translations/en/LC_MESSAGES/django-partial.po
gradefetcher/translations/en/LC_MESSAGES/djangojs-partial.po
gradefetcher/translations/en/LC_MESSAGES/text.po
gradefetcher/translations/es_419/LC_MESSAGES/text.mo
gradefetcher/translations/es_419/LC_MESSAGES/text.po
gradefetcher/translations/fr/LC_MESSAGES/text.mo
gradefetcher/translations/fr/LC_MESSAGES/text.po
gradefetcher/translations/fr_CA/LC_MESSAGES/text.mo
gradefetcher/translations/fr_CA/LC_MESSAGES/text.po
xblock_grade_fetcher-0.5.0.dist-info/LICENSE
xblock_grade_fetcher-0.5.0.dist-info/METADATA
xblock_grade_fetcher-0.5.0.dist-info/WHEEL
xblock_grade_fetcher-0.5.0.dist-info/entry_points.txt
xblock_grade_fetcher-0.5.0.dist-info/top_level.txt
xblock_grade_fetcher-0.5.0.dist-info/RECORD
