Metadata-Version: 2.1
Name: xblock-grade-fetcher
Version: 0.5.0
Summary: Grade Fetcher
License: AGPL v3
License-File: LICENSE
Requires-Dist: XBlock
